nndraw/__init__.py
nndraw/drawing.py
NNDraw-0.1.0.dist-info/METADATA
NNDraw-0.1.0.dist-info/WHEEL
NNDraw-0.1.0.dist-info/top_level.txt
NNDraw-0.1.0.dist-info/RECORD
