Metadata-Version: 2.1
Name: NNDraw
Version: 0.1.0
Summary: A library to draw neural networks based on user parameters
Home-page: https://github.com/akadriu/nndraw
Author: Arbana Kadriu
Author-email: arbana.kadri@gmail.com
Classifier: Programming Language :: Python :: 3
Classifier: Operating System :: OS Independent
Requires-Python: >=3.6
Requires-Dist: matplotlib
Requires-Dist: numpy
Requires-Dist: networkx
